metasyntactic/__init__.py
metasyntactic/base.py
metasyntactic/themes/__init__.py
metasyntactic/themes/abba.py
metasyntactic/themes/afke.py
metasyntactic/themes/alice.py
metasyntactic/themes/alphabet.py
metasyntactic/themes/amber.py
metasyntactic/themes/antlers.py
metasyntactic/themes/asterix.py
metasyntactic/themes/barbapapa.py
metasyntactic/themes/barbarella.py
metasyntactic/themes/batman.py
metasyntactic/themes/ben_and_jerry.py
metasyntactic/themes/bible.py
metasyntactic/themes/booze.py
metasyntactic/themes/bottles.py
metasyntactic/themes/browser.py
metasyntactic/themes/buffy.py
metasyntactic/themes/calvin.py
metasyntactic/themes/camelidae.py
metasyntactic/themes/care_bears.py
metasyntactic/themes/chess.py
metasyntactic/themes/colors.py
metasyntactic/themes/colours.py
metasyntactic/themes/constellations.py
metasyntactic/themes/contrade.py
metasyntactic/themes/contributors.py
metasyntactic/themes/counting_rhyme.py
metasyntactic/themes/counting_to_one.py
metasyntactic/themes/crypto.py
metasyntactic/themes/currency.py
metasyntactic/themes/dancers.py
metasyntactic/themes/debian.py
metasyntactic/themes/dilbert.py
metasyntactic/themes/discworld.py
metasyntactic/themes/doctor_who.py
metasyntactic/themes/donmartin.py
metasyntactic/themes/dwarves.py
metasyntactic/themes/elements.py
metasyntactic/themes/evangelion.py
metasyntactic/themes/fabeltjeskrant.py
metasyntactic/themes/facecards.py
metasyntactic/themes/fawlty_towers.py
metasyntactic/themes/flintstones.py
metasyntactic/themes/foo.py
metasyntactic/themes/french_presidents.py
metasyntactic/themes/garbage.py
metasyntactic/themes/garfield.py
metasyntactic/themes/gems.py
metasyntactic/themes/good_omens.py
metasyntactic/themes/groo.py
metasyntactic/themes/haddock.py
metasyntactic/themes/hhgg.py
metasyntactic/themes/iata.py
metasyntactic/themes/icao.py
metasyntactic/themes/invasions.py
metasyntactic/themes/jabberwocky.py
metasyntactic/themes/jamesbond.py
metasyntactic/themes/jerkcity.py
metasyntactic/themes/linux.py
metasyntactic-1.0.14.dist-info/METADATA
metasyntactic-1.0.14.dist-info/WHEEL
metasyntactic-1.0.14.dist-info/top_level.txt
metasyntactic-1.0.14.dist-info/RECORD
