Metadata-Version: 2.1
Name: metasyntactic
Version: 1.0.14
Summary: metasyntactic - Themed metasyntactic variables names
Home-page: http://github.com/ask/metasyntactic/
Author: Ask Solem
Author-email: ask@celeryproject.org
License: UNKNOWN
Platform: any
Classifier: Development Status :: 4 - Beta
Classifier: License :: OSI Approved :: Artistic License
Classifier: Operating System :: OS Independent
Classifier: Programming Language :: Python
Classifier: Programming Language :: Python :: 3
Classifier: Programming Language :: Python :: 2.7
Classifier: Programming Language :: Python :: 2.6
Classifier: Programming Language :: Python :: 2.5
Classifier: Intended Audience :: Developers
Classifier: Intended Audience :: End Users/Desktop
Classifier: Topic :: Utilities
Classifier: Topic :: Religion
Classifier: Topic :: Other/Nonlisted Topic
Classifier: Topic :: Internet :: Name Service (DNS)
Classifier: Topic :: Games/Entertainment :: Fortune Cookies
Classifier: Topic :: Documentation
Classifier: Topic :: Communications :: Usenet News
Classifier: Topic :: Communications :: Chat
Classifier: Topic :: Artistic Software
Classifier: Programming Language :: Perl
Classifier: Programming Language :: Python
Classifier: Topic :: Software Development :: Libraries :: Python Modules
Classifier: Topic :: Software Development :: Libraries :: Perl Modules
Requires-Dist: six
